{
    "class": "ParticleEmitter",
    "referent": "RBX6D6D5ACF72E54FC6B60D5954D43AD18F",
    "properties": {
        "Acceleration": {
            "X": "0",
            "Y": "0",
            "Z": "0"
        },
        "AttributesSerialize": "AQAAAAkAAABFbWl0Q291bnQGAAAAAAAA8D8=",
        "Brightness": "1",
        "Capabilities": "0",
        "Color": "0 0.996078 0.996078 0.996078 0 1 0.996078 0.996078 0.996078 0 ",
        "DefinesCapabilities": "false",
        "Drag": "0",
        "EmissionDirection": "1",
        "Enabled": "true",
        "FlipbookFramerate": "1 1 ",
        "FlipbookIncompatible": "Particle texture must be 1024 by 1024 to use flipbooks.",
        "FlipbookLayout": "0",
        "FlipbookMode": "0",
        "FlipbookStartRandom": "false",
        "HistoryId": "00000000000000000000000000000000",
        "Lifetime": "0.29 0.29 ",
        "LightEmission": "0",
        "LightInfluence": "0",
        "LockedToPart": "false",
        "Name": "Gradient",
        "Orientation": "0",
        "Rate": "0",
        "RotSpeed": "0 0 ",
        "Rotation": "0 0 ",
        "Shape": "0",
        "ShapeInOut": "0",
        "ShapePartial": "1",
        "ShapeStyle": "0",
        "Size": "0 0.239203 0 0.472125 1.59967 0 1 2.09303 0 ",
        "SourceAssetId": "-1",
        "Speed": "0 0 ",
        "SpreadAngle": {
            "X": "0",
            "Y": "0"
        },
        "Squash": "0 0 0 1 0 0 ",
        "Tags": {},
        "Texture": {
            "url": "rbxassetid://12501965008"
        },
        "TimeScale": "1",
        "Transparency": "0 0 0 0.400697 0 0 1 1 0 ",
        "UniqueId": "451126a27e5c9c2c081e92340000dc1b",
        "VelocityInheritance": "0",
        "WindAffectsDrag": "false",
        "ZOffset": "0"
    }
}