{
    "class": "Script",
    "referent": "RBX34E34C17D7BE4D5EBDFF278BCFE4ADA4",
    "properties": {
        "AttributesSerialize": {},
        "Capabilities": "0",
        "DefinesCapabilities": "false",
        "Disabled": "false",
        "HistoryId": "00000000000000000000000000000000",
        "LinkedSource": {
            "null": {}
        },
        "Name": "Script",
        "RunContext": "0",
        "ScriptGuid": "{DC31F891-69B3-4CF2-8C5A-7908816A2A9D}",
        "Source": "-- Saved by UniversalSynSaveInstance (Join to Copy Games) https://discord.gg/wx4ThpAsmw\n\n-- [FilteringEnabled] Server Scripts are IMPOSSIBLE to save",
        "SourceAssetId": "-1",
        "Tags": {},
        "UniqueId": "451126a27e5c9c2c081e92340000eb45"
    }
}