{
    "class": "Decal",
    "referent": "RBX4FA0173B9DCC465CA94C31DB1F77F02E",
    "properties": {
        "AttributesSerialize": {},
        "Capabilities": "0",
        "Color3": {
            "R": "1",
            "G": "1",
            "B": "1"
        },
        "DefinesCapabilities": "false",
        "Face": "0",
        "HistoryId": "00000000000000000000000000000000",
        "MetalnessMap": {
            "null": {}
        },
        "Name": "Decal",
        "NormalMap": {
            "null": {}
        },
        "RoughnessMap": {
            "null": {}
        },
        "SourceAssetId": "-1",
        "Tags": {},
        "Texture": {
            "url": "http://www.roblox.com/asset/?id=110330590961196"
        },
        "Transparency": "0",
        "UVOffset": {
            "X": "0",
            "Y": "0"
        },
        "UVScale": {
            "X": "1",
            "Y": "1"
        },
        "UniqueId": "451126a27e5c9c2c081e92340000e87f",
        "ZIndex": "1"
    }
}