{
    "class": "Script",
    "referent": "RBX8AFC2527B8804C3D8C37FB21CF805E82",
    "properties": {
        "AttributesSerialize": {},
        "Capabilities": "0",
        "DefinesCapabilities": "false",
        "Disabled": "false",
        "HistoryId": "00000000000000000000000000000000",
        "LinkedSource": {
            "null": {}
        },
        "Name": "Script",
        "RunContext": "0",
        "ScriptGuid": "{ABF6ED82-329C-41CD-8600-88D687CEE313}",
        "Source": "-- Saved by UniversalSynSaveInstance (Join to Copy Games) https://discord.gg/wx4ThpAsmw\n\n-- [FilteringEnabled] Server Scripts are IMPOSSIBLE to save",
        "SourceAssetId": "-1",
        "Tags": {},
        "UniqueId": "451126a27e5c9c2c081e92340000e172"
    }
}