{
    "class": "SelectionBox",
    "referent": "RBXCEAB5A3CC47E4C6685ADA6B60A670353",
    "properties": {
        "Adornee": "null",
        "AttributesSerialize": {},
        "Capabilities": "0",
        "Color3": {
            "R": "1",
            "G": "0",
            "B": "0"
        },
        "DefinesCapabilities": "false",
        "HistoryId": "00000000000000000000000000000000",
        "LineThickness": "0.100000001",
        "Name": "Select",
        "SourceAssetId": "-1",
        "StudioSelectionBox": "false",
        "SurfaceColor3": {
            "R": "0",
            "G": "0",
            "B": "0"
        },
        "SurfaceTransparency": "1",
        "Tags": {},
        "Transparency": "0",
        "UniqueId": "451126a27e5c9c2c081e92340000e813",
        "Visible": "true"
    }
}