{
    "class": "Weld",
    "referent": "RBX6888C6AB27744181AFB41056F3489464",
    "properties": {
        "AttributesSerialize": {},
        "C0": {
            "X": "1.50000048",
            "Y": "1.90734863e-06",
            "Z": "0",
            "R00": "0",
            "R01": "1",
            "R02": "-0",
            "R10": "-1",
            "R11": "0",
            "R12": "0",
            "R20": "0",
            "R21": "0",
            "R22": "1"
        },
        "C1": {
            "X": "0",
            "Y": "0",
            "Z": "0",
            "R00": "1",
            "R01": "0",
            "R02": "0",
            "R10": "0",
            "R11": "1",
            "R12": "0",
            "R20": "0",
            "R21": "0",
            "R22": "1"
        },
        "Capabilities": "0",
        "DefinesCapabilities": "false",
        "Enabled": "true",
        "HistoryId": "451126a27e5c9c2c081e92340000e830",
        "Name": "Part",
        "Part0": "RBXD06A041D5C544D68A42BAAA8246BBA24",
        "Part1": "RBX05AB259D266F49F3AF4BC3FC4511B6B0",
        "SourceAssetId": "-1",
        "Tags": {},
        "UniqueId": "2e688bcb70cf457d083639910000691e"
    }
}