{
    "class": "PackageLink",
    "referent": "RBXBDA0E889DD4F4B6B99D9A8304F4D5CA0",
    "properties": {
        "AttributesSerialize": {},
        "AutoUpdate": "false",
        "Capabilities": "0",
        "DefaultName": {},
        "DefinesCapabilities": "false",
        "HistoryId": "00000000000000000000000000000000",
        "ModifiedState": "1",
        "Name": "PackageLink",
        "PackageIdSerialize": {
            "url": "rbxassetid://16049574146"
        },
        "SerializedDefaultAttributes": {},
        "SourceAssetId": "-1",
        "Tags": {},
        "UniqueId": "451126a27e5c9c2c081e92340000f109",
        "VersionIdSerialize": "20"
    }
}