{
    "class": "Weld",
    "referent": "RBX287A1269FB764E1FA977109D59FC1420",
    "properties": {
        "AttributesSerialize": "AgAAAAkAAABEZWZhdWx0QzAUAAAAAAAAAAAAAAAAAC69OzMAAAAAAACAPwAAAAAAAIA/AAAA\nAAAAgL8AAAAALr07MwkAAABEZWZhdWx0QzEUIHULPQAd2T8AACA3Bw==",
        "C0": {
            "X": "0",
            "Y": "0",
            "Z": "0",
            "R00": "0",
            "R01": "0",
            "R02": "1",
            "R10": "0",
            "R11": "1",
            "R12": "-0",
            "R20": "-1",
            "R21": "0",
            "R22": "0"
        },
        "C1": {
            "X": "0.034047246",
            "Y": "1.69619751",
            "Z": "9.53674316e-06",
            "R00": "0",
            "R01": "1",
            "R02": "0",
            "R10": "1",
            "R11": "0",
            "R12": "0",
            "R20": "0",
            "R21": "0",
            "R22": "-1"
        },
        "Capabilities": "0",
        "DefinesCapabilities": "false",
        "Enabled": "true",
        "HistoryId": "00000000000000000000000000000000",
        "Name": "MeshPart_HitBox_WELD",
        "Part0": "RBXFA7F42FC9F764E02A028C62D75FA4EB8",
        "Part1": "RBX1544093745774F3EAA23AC9339021620",
        "SourceAssetId": "-1",
        "Tags": {},
        "UniqueId": "451126a27e5c9c2c081e92340000e919"
    }
}