{
    "class": "Part",
    "referent": "RBX8B908A74CE3348799E794713E3605D9B",
    "properties": {
        "Anchored": "true",
        "AttributesSerialize": {},
        "AudioCanCollide": "true",
        "BackParamA": "-0.5",
        "BackParamB": "0.5",
        "BackSurface": "1",
        "BackSurfaceInput": "0",
        "BottomParamA": "-0.5",
        "BottomParamB": "0.5",
        "BottomSurface": "1",
        "BottomSurfaceInput": "0",
        "CFrame": {
            "X": "85.4137497",
            "Y": "1.08058512",
            "Z": "-36.9049187",
            "R00": "0.661722064",
            "R01": "-0.333677888",
            "R02": "0.671403706",
            "R10": "0.569516599",
            "R11": "0.806123555",
            "R12": "-0.160672486",
            "R20": "-0.487621486",
            "R21": "0.488696098",
            "R22": "0.723464847"
        },
        "CanCollide": "true",
        "CanQuery": "true",
        "CanTouch": "true",
        "Capabilities": "0",
        "CastShadow": "true",
        "CollisionGroup": "Default",
        "CollisionGroupId": "0",
        "Color3uint8": "4291177296",
        "CustomPhysicalProperties": {
            "CustomPhysics": "false"
        },
        "DefinesCapabilities": "false",
        "EnableFluidForces": "true",
        "FrontParamA": "-0.5",
        "FrontParamB": "0.5",
        "FrontSurface": "1",
        "FrontSurfaceInput": "0",
        "HistoryId": "00000000000000000000000000000000",
        "LeftParamA": "-0.5",
        "LeftParamB": "0.5",
        "LeftSurface": "1",
        "LeftSurfaceInput": "0",
        "Locked": "false",
        "Massless": "false",
        "Material": "256",
        "MaterialVariantSerialized": {},
        "Name": "2",
        "PivotOffset": {
            "X": "0",
            "Y": "0",
            "Z": "0",
            "R00": "1",
            "R01": "0",
            "R02": "0",
            "R10": "0",
            "R11": "1",
            "R12": "0",
            "R20": "0",
            "R21": "0",
            "R22": "1"
        },
        "Reflectance": "0",
        "RightParamA": "-0.5",
        "RightParamB": "0.5",
        "RightSurface": "1",
        "RightSurfaceInput": "0",
        "RootPriority": "0",
        "RotVelocity": {
            "X": "0",
            "Y": "0",
            "Z": "0"
        },
        "SourceAssetId": "-1",
        "Tags": {},
        "TopParamA": "-0.5",
        "TopParamB": "0.5",
        "TopSurface": "1",
        "TopSurfaceInput": "0",
        "Transparency": "0",
        "UniqueId": "451126a27e5c9c2c081e92340000ebbc",
        "Velocity": {
            "X": "0",
            "Y": "0",
            "Z": "0"
        },
        "formFactorRaw": "1",
        "shape": "1",
        "size": {
            "X": "0.169316009",
            "Y": "0.0846580341",
            "Z": "0.169316083"
        }
    }
}