{
    "class": "Script",
    "referent": "RBX12A5B26F6A004100A216EE4CCC7324F6",
    "properties": {
        "AttributesSerialize": {},
        "Capabilities": "0",
        "DefinesCapabilities": "false",
        "Disabled": "false",
        "HistoryId": "00000000000000000000000000000000",
        "LinkedSource": {
            "null": {}
        },
        "Name": "Script",
        "RunContext": "0",
        "ScriptGuid": "{99EC7832-7784-44E4-8E04-DEF2952CAF3F}",
        "Source": "-- Saved by UniversalSynSaveInstance (Join to Copy Games) https://discord.gg/wx4ThpAsmw\n\n-- [FilteringEnabled] Server Scripts are IMPOSSIBLE to save",
        "SourceAssetId": "-1",
        "Tags": {},
        "UniqueId": "451126a27e5c9c2c081e92340000eaff"
    }
}