{
    "class": "UIListLayout",
    "referent": "RBX764BA866FFEE49378549E1D381528E6D",
    "properties": {
        "AttributesSerialize": {},
        "Capabilities": "0",
        "DefinesCapabilities": "false",
        "FillDirection": "0",
        "HistoryId": "00000000000000000000000000000000",
        "HorizontalAlignment": "0",
        "HorizontalFlex": "0",
        "ItemLineAlignment": "0",
        "Name": "UIListLayout",
        "Padding": {
            "S": "0.0250000004",
            "O": "0"
        },
        "SortOrder": "2",
        "SourceAssetId": "-1",
        "Tags": {},
        "UniqueId": "451126a27e5c9c2c081e92340000e9c7",
        "VerticalAlignment": "0",
        "VerticalFlex": "0",
        "Wraps": "false"
    }
}